pygments_git/__init__.py
pygments_git/py.typed
pygments_git-1.9.0.dist-info/licenses/LICENSE
pygments_git-1.9.0.dist-info/METADATA
pygments_git-1.9.0.dist-info/WHEEL
pygments_git-1.9.0.dist-info/entry_points.txt
pygments_git-1.9.0.dist-info/top_level.txt
pygments_git-1.9.0.dist-info/RECORD
